{
  "logs": [
    {
      "id": 1,
      "ticker": "AMZN",
      "period": "6mo",
      "created_at_iso": "2026-02-04T14:50:04.610479+05:30",
      "predicted_for_date": "2026-02-05",
      "last_close": 238.6199951171875,
      "predicted_close": 238.4240544841181,
      "status": "pending",
      "actual_close": null,
      "abs_error": null,
      "pct_error": null,
      "direction_correct": null
    },
    {
      "id": 2,
      "ticker": "DIA",
      "period": "6mo",
      "created_at_iso": "2026-02-04T14:50:06.404553+05:30",
      "predicted_for_date": "2026-02-05",
      "last_close": 492.30999755859375,
      "predicted_close": 492.3223882919102,
      "status": "pending",
      "actual_close": null,
      "abs_error": null,
      "pct_error": null,
      "direction_correct": null
    },
    {
      "id": 3,
      "ticker": "GLD",
      "period": "6mo",
      "created_at_iso": "2026-02-04T14:50:07.905062+05:30",
      "predicted_for_date": "2026-02-05",
      "last_close": 454.2900085449219,
      "predicted_close": 455.98411591510774,
      "status": "pending",
      "actual_close": null,
      "abs_error": null,
      "pct_error": null,
      "direction_correct": null
    },
    {
      "id": 4,
      "ticker": "AVGO",
      "period": "6mo",
      "created_at_iso": "2026-02-04T14:50:09.639249+05:30",
      "predicted_for_date": "2026-02-05",
      "last_close": 320.3299865722656,
      "predicted_close": 321.70015254683864,
      "status": "pending",
      "actual_close": null,
      "abs_error": null,
      "pct_error": null,
      "direction_correct": null
    },
    {
      "id": 5,
      "ticker": "GLD",
      "period": "6mo",
      "created_at_iso": "2026-02-04T14:50:10.923488+05:30",
      "predicted_for_date": "2026-02-05",
      "last_close": 454.2900085449219,
      "predicted_close": 455.98411591510774,
      "status": "pending",
      "actual_close": null,
      "abs_error": null,
      "pct_error": null,
      "direction_correct": null
    },
    {
      "id": 6,
      "ticker": "XOM",
      "period": "6mo",
      "created_at_iso": "2026-02-04T14:50:13.316443+05:30",
      "predicted_for_date": "2026-02-05",
      "last_close": 143.72999572753906,
      "predicted_close": 143.79284200670742,
      "status": "pending",
      "actual_close": null,
      "abs_error": null,
      "pct_error": null,
      "direction_correct": null
    },
    {
      "id": 7,
      "ticker": "BRK-B",
      "period": "6mo",
      "created_at_iso": "2026-02-04T14:50:15.081079+05:30",
      "predicted_for_date": "2026-02-05",
      "last_close": 493.739990234375,
      "predicted_close": 493.4269754600005,
      "status": "pending",
      "actual_close": null,
      "abs_error": null,
      "pct_error": null,
      "direction_correct": null
    },
    {
      "id": 8,
      "ticker": "ITC.NS",
      "period": "6mo",
      "created_at_iso": "2026-02-04T14:50:17.125451+05:30",
      "predicted_for_date": "2026-02-05",
      "last_close": 314.04998779296875,
      "predicted_close": 313.6840263190811,
      "status": "pending",
      "actual_close": null,
      "abs_error": null,
      "pct_error": null,
      "direction_correct": null
    },
    {
      "id": 9,
      "ticker": "MRK",
      "period": "6mo",
      "created_at_iso": "2026-02-04T14:50:19.887754+05:30",
      "predicted_for_date": "2026-02-05",
      "last_close": 115.83999633789062,
      "predicted_close": 115.7530694778935,
      "status": "pending",
      "actual_close": null,
      "abs_error": null,
      "pct_error": null,
      "direction_correct": null
    },
    {
      "id": 10,
      "ticker": "IBM",
      "period": "6mo",
      "created_at_iso": "2026-02-04T14:50:22.356561+05:30",
      "predicted_for_date": "2026-02-05",
      "last_close": 294.30999755859375,
      "predicted_close": 293.8636967949726,
      "status": "pending",
      "actual_close": null,
      "abs_error": null,
      "pct_error": null,
      "direction_correct": null
    },
    {
      "id": 11,
      "ticker": "NFLX",
      "period": "6mo",
      "created_at_iso": "2026-02-04T14:50:24.099904+05:30",
      "predicted_for_date": "2026-02-05",
      "last_close": 79.94000244140625,
      "predicted_close": 79.95795932461817,
      "status": "pending",
      "actual_close": null,
      "abs_error": null,
      "pct_error": null,
      "direction_correct": null
    },
    {
      "id": 12,
      "ticker": "ITC.NS",
      "period": "6mo",
      "created_at_iso": "2026-02-04T14:50:24.927665+05:30",
      "predicted_for_date": "2026-02-05",
      "last_close": 314.04998779296875,
      "predicted_close": 313.6840263190811,
      "status": "pending",
      "actual_close": null,
      "abs_error": null,
      "pct_error": null,
      "direction_correct": null
    },
    {
      "id": 13,
      "ticker": "LLY",
      "period": "6mo",
      "created_at_iso": "2026-02-04T14:50:26.567971+05:30",
      "predicted_for_date": "2026-02-05",
      "last_close": 1003.4600219726562,
      "predicted_close": 1003.0462528834414,
      "status": "pending",
      "actual_close": null,
      "abs_error": null,
      "pct_error": null,
      "direction_correct": null
    },
    {
      "id": 14,
      "ticker": "LOW",
      "period": "6mo",
      "created_at_iso": "2026-02-04T14:50:28.189293+05:30",
      "predicted_for_date": "2026-02-05",
      "last_close": 274.8500061035156,
      "predicted_close": 274.3093845140015,
      "status": "pending",
      "actual_close": null,
      "abs_error": null,
      "pct_error": null,
      "direction_correct": null
    },
    {
      "id": 15,
      "ticker": "AMD",
      "period": "6mo",
      "created_at_iso": "2026-02-04T14:50:29.621727+05:30",
      "predicted_for_date": "2026-02-05",
      "last_close": 242.11000061035156,
      "predicted_close": 241.5508648358001,
      "status": "pending",
      "actual_close": null,
      "abs_error": null,
      "pct_error": null,
      "direction_correct": null
    },
    {
      "id": 16,
      "ticker": "AAPL",
      "period": "6mo",
      "created_at_iso": "2026-02-04T14:50:30.658840+05:30",
      "predicted_for_date": "2026-02-05",
      "last_close": 269.4800109863281,
      "predicted_close": 269.20555230774585,
      "status": "pending",
      "actual_close": null,
      "abs_error": null,
      "pct_error": null,
      "direction_correct": null
    },
    {
      "id": 17,
      "ticker": "LOW",
      "period": "6mo",
      "created_at_iso": "2026-02-04T14:50:31.478770+05:30",
      "predicted_for_date": "2026-02-05",
      "last_close": 274.8500061035156,
      "predicted_close": 274.3093845140015,
      "status": "pending",
      "actual_close": null,
      "abs_error": null,
      "pct_error": null,
      "direction_correct": null
    },
    {
      "id": 18,
      "ticker": "PG",
      "period": "6mo",
      "created_at_iso": "2026-02-04T14:50:33.000969+05:30",
      "predicted_for_date": "2026-02-05",
      "last_close": 155.32000732421875,
      "predicted_close": 155.12058600563043,
      "status": "pending",
      "actual_close": null,
      "abs_error": null,
      "pct_error": null,
      "direction_correct": null
    },
    {
      "id": 19,
      "ticker": "MSFT",
      "period": "6mo",
      "created_at_iso": "2026-02-04T14:50:33.716827+05:30",
      "predicted_for_date": "2026-02-05",
      "last_close": 411.2099914550781,
      "predicted_close": 411.31808319197893,
      "status": "pending",
      "actual_close": null,
      "abs_error": null,
      "pct_error": null,
      "direction_correct": null
    },
    {
      "id": 20,
      "ticker": "SBIN.NS",
      "period": "6mo",
      "created_at_iso": "2026-02-04T14:50:35.058445+05:30",
      "predicted_for_date": "2026-02-05",
      "last_close": 1068.0,
      "predicted_close": 1065.442325694166,
      "status": "pending",
      "actual_close": null,
      "abs_error": null,
      "pct_error": null,
      "direction_correct": null
    },
    {
      "id": 21,
      "ticker": "AMD",
      "period": "6mo",
      "created_at_iso": "2026-02-04T14:50:35.969153+05:30",
      "predicted_for_date": "2026-02-05",
      "last_close": 242.11000061035156,
      "predicted_close": 241.5508648358001,
      "status": "pending",
      "actual_close": null,
      "abs_error": null,
      "pct_error": null,
      "direction_correct": null
    },
    {
      "id": 22,
      "ticker": "GOOGL",
      "period": "6mo",
      "created_at_iso": "2026-02-04T14:50:36.920537+05:30",
      "predicted_for_date": "2026-02-05",
      "last_close": 339.7099914550781,
      "predicted_close": 338.92111803895307,
      "status": "pending",
      "actual_close": null,
      "abs_error": null,
      "pct_error": null,
      "direction_correct": null
    },
    {
      "id": 23,
      "ticker": "SPY",
      "period": "6mo",
      "created_at_iso": "2026-02-04T14:50:38.711970+05:30",
      "predicted_for_date": "2026-02-05",
      "last_close": 689.530029296875,
      "predicted_close": 690.2946871587349,
      "status": "pending",
      "actual_close": null,
      "abs_error": null,
      "pct_error": null,
      "direction_correct": null
    },
    {
      "id": 24,
      "ticker": "GOOGL",
      "period": "6mo",
      "created_at_iso": "2026-02-04T14:50:39.588048+05:30",
      "predicted_for_date": "2026-02-05",
      "last_close": 339.7099914550781,
      "predicted_close": 338.92111803895307,
      "status": "pending",
      "actual_close": null,
      "abs_error": null,
      "pct_error": null,
      "direction_correct": null
    },
    {
      "id": 25,
      "ticker": "AMGN",
      "period": "6mo",
      "created_at_iso": "2026-02-04T14:50:42.058334+05:30",
      "predicted_for_date": "2026-02-05",
      "last_close": 338.5899963378906,
      "predicted_close": 338.6175103537255,
      "status": "pending",
      "actual_close": null,
      "abs_error": null,
      "pct_error": null,
      "direction_correct": null
    },
    {
      "id": 26,
      "ticker": "INTC",
      "period": "6mo",
      "created_at_iso": "2026-02-04T14:50:43.849360+05:30",
      "predicted_for_date": "2026-02-05",
      "last_close": 49.25,
      "predicted_close": 49.314388072760835,
      "status": "pending",
      "actual_close": null,
      "abs_error": null,
      "pct_error": null,
      "direction_correct": null
    },
    {
      "id": 27,
      "ticker": "TLT",
      "period": "6mo",
      "created_at_iso": "2026-02-04T14:50:46.204356+05:30",
      "predicted_for_date": "2026-02-05",
      "last_close": 86.76000213623047,
      "predicted_close": 86.76815672159405,
      "status": "pending",
      "actual_close": null,
      "abs_error": null,
      "pct_error": null,
      "direction_correct": null
    },
    {
      "id": 28,
      "ticker": "LICI.NS",
      "period": "6mo",
      "created_at_iso": "2026-02-04T14:50:47.964555+05:30",
      "predicted_for_date": "2026-02-05",
      "last_close": 836.2999877929688,
      "predicted_close": 832.4478064786607,
      "status": "pending",
      "actual_close": null,
      "abs_error": null,
      "pct_error": null,
      "direction_correct": null
    },
    {
      "id": 29,
      "ticker": "HINDUNILVR.NS",
      "period": "6mo",
      "created_at_iso": "2026-02-04T14:50:49.594957+05:30",
      "predicted_for_date": "2026-02-05",
      "last_close": 2371.60009765625,
      "predicted_close": 2370.293908222079,
      "status": "pending",
      "actual_close": null,
      "abs_error": null,
      "pct_error": null,
      "direction_correct": null
    },
    {
      "id": 30,
      "ticker": "HINDUNILVR.NS",
      "period": "6mo",
      "created_at_iso": "2026-02-04T14:50:50.721457+05:30",
      "predicted_for_date": "2026-02-05",
      "last_close": 2371.60009765625,
      "predicted_close": 2370.293908222079,
      "status": "pending",
      "actual_close": null,
      "abs_error": null,
      "pct_error": null,
      "direction_correct": null
    },
    {
      "id": 31,
      "ticker": "TLT",
      "period": "6mo",
      "created_at_iso": "2026-02-04T14:50:51.969324+05:30",
      "predicted_for_date": "2026-02-05",
      "last_close": 86.76000213623047,
      "predicted_close": 86.76815672159405,
      "status": "pending",
      "actual_close": null,
      "abs_error": null,
      "pct_error": null,
      "direction_correct": null
    },
    {
      "id": 32,
      "ticker": "PG",
      "period": "6mo",
      "created_at_iso": "2026-02-04T14:50:52.772791+05:30",
      "predicted_for_date": "2026-02-05",
      "last_close": 155.32000732421875,
      "predicted_close": 155.12058600563043,
      "status": "pending",
      "actual_close": null,
      "abs_error": null,
      "pct_error": null,
      "direction_correct": null
    },
    {
      "id": 33,
      "ticker": "TLT",
      "period": "6mo",
      "created_at_iso": "2026-02-04T14:50:53.627274+05:30",
      "predicted_for_date": "2026-02-05",
      "last_close": 86.76000213623047,
      "predicted_close": 86.76815672159405,
      "status": "pending",
      "actual_close": null,
      "abs_error": null,
      "pct_error": null,
      "direction_correct": null
    },
    {
      "id": 34,
      "ticker": "TXN",
      "period": "6mo",
      "created_at_iso": "2026-02-04T14:50:55.529890+05:30",
      "predicted_for_date": "2026-02-05",
      "last_close": 225.2100067138672,
      "predicted_close": 224.32078424532767,
      "status": "pending",
      "actual_close": null,
      "abs_error": null,
      "pct_error": null,
      "direction_correct": null
    },
    {
      "id": 35,
      "ticker": "UNG",
      "period": "6mo",
      "created_at_iso": "2026-02-04T14:50:57.585334+05:30",
      "predicted_for_date": "2026-02-05",
      "last_close": 12.979999542236328,
      "predicted_close": 13.054453141146595,
      "status": "pending",
      "actual_close": null,
      "abs_error": null,
      "pct_error": null,
      "direction_correct": null
    },
    {
      "id": 36,
      "ticker": "IWM",
      "period": "6mo",
      "created_at_iso": "2026-02-04T14:51:00.746475+05:30",
      "predicted_for_date": "2026-02-05",
      "last_close": 262.7799987792969,
      "predicted_close": 262.0516984907091,
      "status": "pending",
      "actual_close": null,
      "abs_error": null,
      "pct_error": null,
      "direction_correct": null
    },
    {
      "id": 37,
      "ticker": "JPM",
      "period": "6mo",
      "created_at_iso": "2026-02-04T14:51:02.598904+05:30",
      "predicted_for_date": "2026-02-05",
      "last_close": 314.8500061035156,
      "predicted_close": 315.22740276822697,
      "status": "pending",
      "actual_close": null,
      "abs_error": null,
      "pct_error": null,
      "direction_correct": null
    },
    {
      "id": 38,
      "ticker": "AMZN",
      "period": "6mo",
      "created_at_iso": "2026-02-04T14:51:03.419189+05:30",
      "predicted_for_date": "2026-02-05",
      "last_close": 238.6199951171875,
      "predicted_close": 238.4240544841181,
      "status": "pending",
      "actual_close": null,
      "abs_error": null,
      "pct_error": null,
      "direction_correct": null
    },
    {
      "id": 39,
      "ticker": "BHARTIARTL.NS",
      "period": "6mo",
      "created_at_iso": "2026-02-04T14:51:05.055397+05:30",
      "predicted_for_date": "2026-02-05",
      "last_close": 2032.4000244140625,
      "predicted_close": 2032.4010078555993,
      "status": "pending",
      "actual_close": null,
      "abs_error": null,
      "pct_error": null,
      "direction_correct": null
    },
    {
      "id": 40,
      "ticker": "META",
      "period": "6mo",
      "created_at_iso": "2026-02-04T14:51:07.003322+05:30",
      "predicted_for_date": "2026-02-05",
      "last_close": 691.7000122070312,
      "predicted_close": 689.5989678496658,
      "status": "pending",
      "actual_close": null,
      "abs_error": null,
      "pct_error": null,
      "direction_correct": null
    },
    {
      "id": 41,
      "ticker": "LOW",
      "period": "6mo",
      "created_at_iso": "2026-02-04T14:51:08.331435+05:30",
      "predicted_for_date": "2026-02-05",
      "last_close": 274.8500061035156,
      "predicted_close": 274.3093845140015,
      "status": "pending",
      "actual_close": null,
      "abs_error": null,
      "pct_error": null,
      "direction_correct": null
    },
    {
      "id": 42,
      "ticker": "TLT",
      "period": "6mo",
      "created_at_iso": "2026-02-04T14:51:09.356197+05:30",
      "predicted_for_date": "2026-02-05",
      "last_close": 86.76000213623047,
      "predicted_close": 86.76815672159405,
      "status": "pending",
      "actual_close": null,
      "abs_error": null,
      "pct_error": null,
      "direction_correct": null
    },
    {
      "id": 43,
      "ticker": "V",
      "period": "6mo",
      "created_at_iso": "2026-02-04T14:51:11.505021+05:30",
      "predicted_for_date": "2026-02-05",
      "last_close": 328.92999267578125,
      "predicted_close": 329.5673368897693,
      "status": "pending",
      "actual_close": null,
      "abs_error": null,
      "pct_error": null,
      "direction_correct": null
    },
    {
      "id": 44,
      "ticker": "HINDUNILVR.NS",
      "period": "6mo",
      "created_at_iso": "2026-02-04T14:51:12.516628+05:30",
      "predicted_for_date": "2026-02-05",
      "last_close": 2371.39990234375,
      "predicted_close": 2370.095047465757,
      "status": "pending",
      "actual_close": null,
      "abs_error": null,
      "pct_error": null,
      "direction_correct": null
    },
    {
      "id": 45,
      "ticker": "IBM",
      "period": "6mo",
      "created_at_iso": "2026-02-04T14:51:13.434148+05:30",
      "predicted_for_date": "2026-02-05",
      "last_close": 294.30999755859375,
      "predicted_close": 293.8636967949726,
      "status": "pending",
      "actual_close": null,
      "abs_error": null,
      "pct_error": null,
      "direction_correct": null
    },
    {
      "id": 46,
      "ticker": "LICI.NS",
      "period": "6mo",
      "created_at_iso": "2026-02-04T14:51:14.463518+05:30",
      "predicted_for_date": "2026-02-05",
      "last_close": 836.25,
      "predicted_close": 832.3979316967311,
      "status": "pending",
      "actual_close": null,
      "abs_error": null,
      "pct_error": null,
      "direction_correct": null
    },
    {
      "id": 47,
      "ticker": "MA",
      "period": "6mo",
      "created_at_iso": "2026-02-04T14:51:16.750706+05:30",
      "predicted_for_date": "2026-02-05",
      "last_close": 550.719970703125,
      "predicted_close": 550.7981600123559,
      "status": "pending",
      "actual_close": null,
      "abs_error": null,
      "pct_error": null,
      "direction_correct": null
    },
    {
      "id": 48,
      "ticker": "IBM",
      "period": "6mo",
      "created_at_iso": "2026-02-04T14:51:17.665816+05:30",
      "predicted_for_date": "2026-02-05",
      "last_close": 294.30999755859375,
      "predicted_close": 293.8636967949726,
      "status": "pending",
      "actual_close": null,
      "abs_error": null,
      "pct_error": null,
      "direction_correct": null
    },
    {
      "id": 49,
      "ticker": "INTC",
      "period": "6mo",
      "created_at_iso": "2026-02-04T14:51:18.670501+05:30",
      "predicted_for_date": "2026-02-05",
      "last_close": 49.25,
      "predicted_close": 49.314388072760835,
      "status": "pending",
      "actual_close": null,
      "abs_error": null,
      "pct_error": null,
      "direction_correct": null
    },
    {
      "id": 50,
      "ticker": "INFY.NS",
      "period": "6mo",
      "created_at_iso": "2026-02-04T14:51:20.389422+05:30",
      "predicted_for_date": "2026-02-05",
      "last_close": 1539.4000244140625,
      "predicted_close": 1534.805561933125,
      "status": "pending",
      "actual_close": null,
      "abs_error": null,
      "pct_error": null,
      "direction_correct": null
    }
  ]
}